{
  "schemaVersion": "almanac-attestation-v1",
  "date": "2026-05-26",
  "verifyAt": "https://almanac-staging.vercel.app/verify",
  "instructions": "Each entry below is a SHA-256 hash of a prediction published on this date. Visit verifyAt to recompute any hash from its prediction's canonical input. A prediction whose live hash no longer matches the value here has been tampered with. The rootHash is sha256 of the sorted concatenation of all entry hashes — change one and it flips.",
  "count": 13,
  "rootHash": "afcca1b7d09799ca24d544fc86867a6e6727a9f1d5322a3671a9f04313035139",
  "predictions": [
    {
      "id": "cm63db7af8989b936a8e0584ab",
      "hash": "15bcc6e54a09746225bf271ba8f861612cfdad0a5aa39ed94c4da532a0b6dbc2",
      "predictionSchemaVersion": "betclarity-prediction-v2",
      "publishedAt": "2026-05-26T03:00:04.120Z"
    },
    {
      "id": "cm34dc9b4aeb2c8873d22122ab",
      "hash": "1ba0c03a3127af3df1c0d2bc323f59f60eb553c0df981e05af858584631573c6",
      "predictionSchemaVersion": "betclarity-prediction-v2",
      "publishedAt": "2026-05-26T03:00:04.120Z"
    },
    {
      "id": "cmb79f256671f1d2d65c960aab",
      "hash": "43032d85be967cacd72d20fbded69477208bd1d5cf5a4bca1a7406484cf1d2c9",
      "predictionSchemaVersion": "betclarity-prediction-v2",
      "publishedAt": "2026-05-26T03:00:04.120Z"
    },
    {
      "id": "cmc7cad695196a4acbcecf9fab",
      "hash": "50a383e74d1df4bf7ddc925bc6c92ba761d0a6df49c0aec5ef7c614525950ea5",
      "predictionSchemaVersion": "betclarity-prediction-v2",
      "publishedAt": "2026-05-26T03:00:04.120Z"
    },
    {
      "id": "cm8dc77985cc5815fc08a4eaab",
      "hash": "66541bd81751552208d9cb63e4e83bc9457ed6eae78d9c34d8a55383e0aa0901",
      "predictionSchemaVersion": "betclarity-prediction-v2",
      "publishedAt": "2026-05-26T03:00:04.120Z"
    },
    {
      "id": "cm24ff6ddad3611d61e95bd2ab",
      "hash": "66f4b44b136b1cf66a1847b5f832de93dc698f6066a68b1818af6cdfdd43080d",
      "predictionSchemaVersion": "betclarity-prediction-v2",
      "publishedAt": "2026-05-26T03:00:04.120Z"
    },
    {
      "id": "cm653cb3a9de79a65d5f638fab",
      "hash": "70a99db6b62154f3be96fd6b3c954fccb185fb18fd82dea79ba248026f080da0",
      "predictionSchemaVersion": "betclarity-prediction-v2",
      "publishedAt": "2026-05-26T03:00:04.120Z"
    },
    {
      "id": "cm259e2da73fe664da37427fab",
      "hash": "7a9125c34161a4772fcd959fc7440451602014b4c9c25424c3c25dba580e6309",
      "predictionSchemaVersion": "betclarity-prediction-v2",
      "publishedAt": "2026-05-26T03:00:04.120Z"
    },
    {
      "id": "cm31af03d2d56620d8291d06ab",
      "hash": "874e94ed4a53c6fa0fb9ecf2c435bf3251eec1d68c31159cf188bcf89a37129f",
      "predictionSchemaVersion": "betclarity-prediction-v2",
      "publishedAt": "2026-05-26T03:00:04.120Z"
    },
    {
      "id": "cm839a512176d1430df64d51ab",
      "hash": "a21353da1fc8b6b04ef503637d3af60861d77a8d07e7f84aa2b5e3ab97fa977c",
      "predictionSchemaVersion": "betclarity-prediction-v2",
      "publishedAt": "2026-05-26T03:00:04.120Z"
    },
    {
      "id": "cme11d366230365236294949ab",
      "hash": "c39b3ff6ccfa672bc31c9d8d4944405be6283d13e57e48f8c0439a0245def342",
      "predictionSchemaVersion": "betclarity-prediction-v2",
      "publishedAt": "2026-05-26T03:00:04.120Z"
    },
    {
      "id": "cm500413c6eddce4a749d782ab",
      "hash": "d1fc962fe85bfea4f7feb684c143fcfe67f0f2bc4ae1c2cbb6e5c3969b8b758a",
      "predictionSchemaVersion": "betclarity-prediction-v2",
      "publishedAt": "2026-05-26T03:00:04.120Z"
    },
    {
      "id": "cmf53e0838479e07770c4d6aab",
      "hash": "d9b6ec3513daff0d9536e2baab87ad45b7842f22ef7bfc30a85ad792a458d5a7",
      "predictionSchemaVersion": "betclarity-prediction-v2",
      "publishedAt": "2026-05-26T03:00:04.120Z"
    }
  ]
}
