{
  "schemaVersion": "almanac-attestation-v1",
  "date": "2026-02-20",
  "verifyAt": "https://almanac-staging.vercel.app/verify",
  "instructions": "Each entry below is a SHA-256 hash of a prediction published on this date. Visit verifyAt to recompute any hash from its prediction's canonical input. A prediction whose live hash no longer matches the value here has been tampered with. The rootHash is sha256 of the sorted concatenation of all entry hashes — change one and it flips.",
  "count": 1,
  "rootHash": "2968817ccee4824c44a9dd54911fd84e4ae553e5c4288fe4568a7408cea13ad6",
  "predictions": [
    {
      "id": "cmowwzsdo00easotzhim5uclu",
      "hash": "69d1624c5ced27321438c8573e82df4ee2be80060067c64bccfc8fed29f29d39",
      "predictionSchemaVersion": "betclarity-prediction-v2",
      "publishedAt": "2026-02-20T10:11:00.000Z"
    }
  ]
}
